mkdocs_cc_license_plugin/__init__.py
mkdocs_cc_license_plugin/plugin.py
mkdocs_cc_license_plugin-1.0.1.dist-info/licenses/LICENSE
mkdocs_cc_license_plugin-1.0.1.dist-info/METADATA
mkdocs_cc_license_plugin-1.0.1.dist-info/WHEEL
mkdocs_cc_license_plugin-1.0.1.dist-info/entry_points.txt
mkdocs_cc_license_plugin-1.0.1.dist-info/top_level.txt
mkdocs_cc_license_plugin-1.0.1.dist-info/RECORD
