Metadata-Version: 2.4
Name: mkdocs-cc-license-plugin
Version: 1.0.1
Summary: MkDocs plugin for automatic Creative Commons license management
Home-page: https://github.com/JM2K69/mkdocs-cc-license-plugin
Author: Jérôme Bezet-Torres
Author-email: Jérôme Bezet-Torres <bezettorres.jerome@gmail.com>
License: MIT
Project-URL: Homepage, https://github.com/JM2K69/mkdocs-cc-license-plugin
Project-URL: Documentation, https://github.com/JM2K69/mkdocs-cc-license-plugin#readme
Project-URL: Repository, https://github.com/JM2K69/mkdocs-cc-license-plugin
Project-URL: Issues, https://github.com/JM2K69/mkdocs-cc-license-plugin/issues
Classifier: Development Status :: 4 - Beta
Classifier: Intended Audience :: Developers
Classifier: License :: OSI Approved :: MIT License
Classifier: Operating System :: OS Independent
Classifier: Programming Language :: Python :: 3
Classifier: Programming Language :: Python :: 3.7
Classifier: Programming Language :: Python :: 3.8
Classifier: Programming Language :: Python :: 3.9
Classifier: Programming Language :: Python :: 3.10
Classifier: Programming Language :: Python :: 3.11
Classifier: Topic :: Documentation
Classifier: Topic :: Software Development :: Documentation
Requires-Python: >=3.7
License-File: LICENSE
Requires-Dist: mkdocs>=1.0
Requires-Dist: Jinja2>=2.10
Provides-Extra: dev
Requires-Dist: pytest>=6.0; extra == "dev"
Requires-Dist: mkdocs-material>=8.0; extra == "dev"
Dynamic: author
Dynamic: home-page
Dynamic: license-file
Dynamic: requires-python
